[
  {
    "condition": "Near Mint",
    "variant": "Normal",
    "language": "English",
    "quantity": 1,
    "title": "Aatchik, Emerald Radian",
    "listingType": "ListingWithoutPhotos",
    "customListingId": "0",
    "purchasePrice": 0.05,
    "shippingPrice": 1.31,
    "orderDate": "2025-05-28T01:00:44.687+00:00"
  },
  {
    "condition": "Near Mint",
    "variant": "Normal",
    "language": "English",
    "quantity": 1,
    "title": "Aatchik, Emerald Radian",
    "listingType": "ListingWithoutPhotos",
    "customListingId": "0",
    "purchasePrice": 0.15,
    "shippingPrice": 1.31,
    "orderDate": "2025-05-27T22:04:48.82+00:00"
  },
  {
    "condition": "Near Mint",
    "variant": "Normal",
    "language": "English",
    "quantity": 1,
    "title": "Aatchik, Emerald Radian",
    "listingType": "ListingWithoutPhotos",
    "customListingId": "0",
    "purchasePrice": 0.15,
    "shippingPrice": 0,
    "orderDate": "2025-05-26T20:26:57.27+00:00"
  },
  {
    "condition": "Near Mint",
    "variant": "Normal",
    "language": "English",
    "quantity": 1,
    "title": "Aatchik, Emerald Radian",
    "listingType": "ListingWithoutPhotos",
    "customListingId": "0",
    "purchasePrice": 0.15,
    "shippingPrice": 0,
    "orderDate": "2025-05-26T19:36:45.237+00:00"
  },
  {
    "condition": "Near Mint",
    "variant": "Normal",
    "language": "English",
    "quantity": 1,
    "title": "Aatchik, Emerald Radian",
    "listingType": "ListingWithoutPhotos",
    "customListingId": "0",
    "purchasePrice": 0.14,
    "shippingPrice": 0,
    "orderDate": "2025-05-26T04:54:59.96+00:00"
  },
  {
    "condition": "Near Mint",
    "variant": "Normal",
    "language": "English",
    "quantity": 1,
    "title": "Aatchik, Emerald Radian",
    "listingType": "ListingWithoutPhotos",
    "customListingId": "0",
    "purchasePrice": 0.08,
    "shippingPrice": 1.31,
    "orderDate": "2025-05-25T23:11:53.18+00:00"
  },
  {
    "condition": "Near Mint",
    "variant": "Normal",
    "language": "English",
    "quantity": 1,
    "title": "Aatchik, Emerald Radian",
    "listingType": "ListingWithoutPhotos",
    "customListingId": "0",
    "purchasePrice": 0.15,
    "shippingPrice": 0,
    "orderDate": "2025-05-25T21:11:16.54+00:00"
  },
  {
    "condition": "Near Mint",
    "variant": "Normal",
    "language": "English",
    "quantity": 1,
    "title": "Aatchik, Emerald Radian",
    "listingType": "ListingWithoutPhotos",
    "customListingId": "0",
    "purchasePrice": 0.14,
    "shippingPrice": 1.31,
    "orderDate": "2025-05-25T20:54:02.047+00:00"
  },
  {
    "condition": "Near Mint",
    "variant": "Normal",
    "language": "English",
    "quantity": 1,
    "title": "Aatchik, Emerald Radian",
    "listingType": "ListingWithoutPhotos",
    "customListingId": "0",
    "purchasePrice": 0.3,
    "shippingPrice": 0,
    "orderDate": "2025-05-25T19:26:41.33+00:00"
  },
  {
    "condition": "Near Mint",
    "variant": "Normal",
    "language": "English",
    "quantity": 1,
    "title": "Aatchik, Emerald Radian",
    "listingType": "ListingWithoutPhotos",
    "customListingId": "0",
    "purchasePrice": 0.15,
    "shippingPrice": 0,
    "orderDate": "2025-05-25T09:50:52.627+00:00"
  },
  {
    "condition": "Near Mint",
    "variant": "Normal",
    "language": "English",
    "quantity": 1,
    "title": "Aatchik, Emerald Radian",
    "listingType": "ListingWithoutPhotos",
    "customListingId": "0",
    "purchasePrice": 0.15,
    "shippingPrice": 0,
    "orderDate": "2025-05-25T05:04:57.973+00:00"
  },
  {
    "condition": "Near Mint",
    "variant": "Normal",
    "language": "English",
    "quantity": 1,
    "title": "Aatchik, Emerald Radian",
    "listingType": "ListingWithoutPhotos",
    "customListingId": "0",
    "purchasePrice": 0.03,
    "shippingPrice": 0.99,
    "orderDate": "2025-05-25T03:21:39.02+00:00"
  },
  {
    "condition": "Near Mint",
    "variant": "Normal",
    "language": "English",
    "quantity": 1,
    "title": "Aatchik, Emerald Radian",
    "listingType": "ListingWithoutPhotos",
    "customListingId": "0",
    "purchasePrice": 0.15,
    "shippingPrice": 0,
    "orderDate": "2025-05-25T00:05:57.28+00:00"
  },
  {
    "condition": "Near Mint",
    "variant": "Normal",
    "language": "English",
    "quantity": 1,
    "title": "Aatchik, Emerald Radian",
    "listingType": "ListingWithoutPhotos",
    "customListingId": "0",
    "purchasePrice": 0.15,
    "shippingPrice": 0,
    "orderDate": "2025-05-24T23:29:34.833+00:00"
  },
  {
    "condition": "Near Mint",
    "variant": "Normal",
    "language": "English",
    "quantity": 1,
    "title": "Aatchik, Emerald Radian",
    "listingType": "ListingWithoutPhotos",
    "customListingId": "0",
    "purchasePrice": 0.15,
    "shippingPrice": 0,
    "orderDate": "2025-05-24T16:08:06.453+00:00"
  },
  {
    "condition": "Near Mint",
    "variant": "Normal",
    "language": "English",
    "quantity": 1,
    "title": "Aatchik, Emerald Radian",
    "listingType": "ListingWithoutPhotos",
    "customListingId": "0",
    "purchasePrice": 0.15,
    "shippingPrice": 0,
    "orderDate": "2025-05-24T00:43:26.177+00:00"
  },
  {
    "condition": "Near Mint",
    "variant": "Normal",
    "language": "English",
    "quantity": 1,
    "title": "Aatchik, Emerald Radian",
    "listingType": "ListingWithoutPhotos",
    "customListingId": "0",
    "purchasePrice": 0.15,
    "shippingPrice": 0,
    "orderDate": "2025-05-23T08:39:04.58+00:00"
  },
  {
    "condition": "Near Mint",
    "variant": "Normal",
    "language": "English",
    "quantity": 1,
    "title": "Aatchik, Emerald Radian",
    "listingType": "ListingWithoutPhotos",
    "customListingId": "0",
    "purchasePrice": 0.09,
    "shippingPrice": 1.31,
    "orderDate": "2025-05-23T04:48:14.527+00:00"
  },
  {
    "condition": "Near Mint",
    "variant": "Normal",
    "language": "English",
    "quantity": 1,
    "title": "Aatchik, Emerald Radian",
    "listingType": "ListingWithoutPhotos",
    "customListingId": "0",
    "purchasePrice": 0.15,
    "shippingPrice": 0,
    "orderDate": "2025-05-23T02:06:26.143+00:00"
  },
  {
    "condition": "Near Mint",
    "variant": "Normal",
    "language": "English",
    "quantity": 2,
    "title": "Aatchik, Emerald Radian",
    "listingType": "ListingWithoutPhotos",
    "customListingId": "0",
    "purchasePrice": 0.14,
    "shippingPrice": 0,
    "orderDate": "2025-05-23T02:06:25.967+00:00"
  },
  {
    "condition": "Near Mint",
    "variant": "Normal",
    "language": "English",
    "quantity": 1,
    "title": "Aatchik, Emerald Radian",
    "listingType": "ListingWithoutPhotos",
    "customListingId": "0",
    "purchasePrice": 0.14,
    "shippingPrice": 0,
    "orderDate": "2025-05-23T02:06:25.887+00:00"
  },
  {
    "condition": "Near Mint",
    "variant": "Normal",
    "language": "English",
    "quantity": 1,
    "title": "Aatchik, Emerald Radian",
    "listingType": "ListingWithoutPhotos",
    "customListingId": "0",
    "purchasePrice": 0.08,
    "shippingPrice": 2,
    "orderDate": "2025-05-23T01:10:59.137+00:00"
  },
  {
    "condition": "Near Mint",
    "variant": "Normal",
    "language": "English",
    "quantity": 2,
    "title": "Aatchik, Emerald Radian",
    "listingType": "ListingWithoutPhotos",
    "customListingId": "0",
    "purchasePrice": 0.14,
    "shippingPrice": 2.8,
    "orderDate": "2025-05-22T20:58:17.86+00:00"
  },
  {
    "condition": "Near Mint",
    "variant": "Normal",
    "language": "English",
    "quantity": 1,
    "title": "Aatchik, Emerald Radian",
    "listingType": "ListingWithoutPhotos",
    "customListingId": "0",
    "purchasePrice": 0.15,
    "shippingPrice": 0,
    "orderDate": "2025-05-22T04:27:33.237+00:00"
  },
  {
    "condition": "Near Mint",
    "variant": "Normal",
    "language": "English",
    "quantity": 1,
    "title": "Aatchik, Emerald Radian",
    "listingType": "ListingWithoutPhotos",
    "customListingId": "0",
    "purchasePrice": 0.15,
    "shippingPrice": 0,
    "orderDate": "2025-05-21T02:48:06.853+00:00"
  },
  {
    "condition": "Near Mint",
    "variant": "Normal",
    "language": "English",
    "quantity": 1,
    "title": "Aatchik, Emerald Radian",
    "listingType": "ListingWithoutPhotos",
    "customListingId": "0",
    "purchasePrice": 0.15,
    "shippingPrice": 0,
    "orderDate": "2025-05-21T02:22:29.303+00:00"
  },
  {
    "condition": "Near Mint",
    "variant": "Normal",
    "language": "English",
    "quantity": 1,
    "title": "Aatchik, Emerald Radian",
    "listingType": "ListingWithoutPhotos",
    "customListingId": "0",
    "purchasePrice": 0.15,
    "shippingPrice": 0,
    "orderDate": "2025-05-20T19:39:45.82+00:00"
  },
  {
    "condition": "Near Mint",
    "variant": "Normal",
    "language": "English",
    "quantity": 1,
    "title": "Aatchik, Emerald Radian",
    "listingType": "ListingWithoutPhotos",
    "customListingId": "0",
    "purchasePrice": 0.15,
    "shippingPrice": 0,
    "orderDate": "2025-05-20T19:21:40.86+00:00"
  },
  {
    "condition": "Near Mint",
    "variant": "Normal",
    "language": "English",
    "quantity": 2,
    "title": "Aatchik, Emerald Radian",
    "listingType": "ListingWithoutPhotos",
    "customListingId": "0",
    "purchasePrice": 0.18,
    "shippingPrice": 1.27,
    "orderDate": "2025-05-20T15:01:07.56+00:00"
  },
  {
    "condition": "Near Mint",
    "variant": "Normal",
    "language": "English",
    "quantity": 1,
    "title": "Aatchik, Emerald Radian",
    "listingType": "ListingWithoutPhotos",
    "customListingId": "0",
    "purchasePrice": 0.15,
    "shippingPrice": 0,
    "orderDate": "2025-05-20T00:11:25.047+00:00"
  },
  {
    "condition": "Near Mint",
    "variant": "Normal",
    "language": "English",
    "quantity": 1,
    "title": "Aatchik, Emerald Radian",
    "listingType": "ListingWithoutPhotos",
    "customListingId": "0",
    "purchasePrice": 0.13,
    "shippingPrice": 0,
    "orderDate": "2025-05-19T17:01:08.503+00:00"
  },
  {
    "condition": "Near Mint",
    "variant": "Normal",
    "language": "English",
    "quantity": 4,
    "title": "Aatchik, Emerald Radian",
    "listingType": "ListingWithoutPhotos",
    "customListingId": "0",
    "purchasePrice": 0.18,
    "shippingPrice": 0,
    "orderDate": "2025-05-19T06:59:58.397+00:00"
  },
  {
    "condition": "Near Mint",
    "variant": "Normal",
    "language": "English",
    "quantity": 1,
    "title": "Aatchik, Emerald Radian",
    "listingType": "ListingWithoutPhotos",
    "customListingId": "0",
    "purchasePrice": 0.06,
    "shippingPrice": 0,
    "orderDate": "2025-05-19T06:41:20.693+00:00"
  },
  {
    "condition": "Near Mint",
    "variant": "Normal",
    "language": "English",
    "quantity": 4,
    "title": "Aatchik, Emerald Radian",
    "listingType": "ListingWithoutPhotos",
    "customListingId": "0",
    "purchasePrice": 0.15,
    "shippingPrice": 0,
    "orderDate": "2025-05-18T08:16:17.763+00:00"
  },
  {
    "condition": "Near Mint",
    "variant": "Normal",
    "language": "English",
    "quantity": 1,
    "title": "Aatchik, Emerald Radian",
    "listingType": "ListingWithoutPhotos",
    "customListingId": "0",
    "purchasePrice": 0.15,
    "shippingPrice": 0,
    "orderDate": "2025-05-18T05:49:19.563+00:00"
  },
  {
    "condition": "Near Mint",
    "variant": "Normal",
    "language": "English",
    "quantity": 1,
    "title": "Aatchik, Emerald Radian",
    "listingType": "ListingWithoutPhotos",
    "customListingId": "0",
    "purchasePrice": 0.07,
    "shippingPrice": 0,
    "orderDate": "2025-05-18T03:23:23.957+00:00"
  },
  {
    "condition": "Near Mint",
    "variant": "Normal",
    "language": "English",
    "quantity": 1,
    "title": "Aatchik, Emerald Radian",
    "listingType": "ListingWithoutPhotos",
    "customListingId": "0",
    "purchasePrice": 0.16,
    "shippingPrice": 0,
    "orderDate": "2025-05-18T00:52:53.28+00:00"
  },
  {
    "condition": "Near Mint",
    "variant": "Normal",
    "language": "English",
    "quantity": 3,
    "title": "Aatchik, Emerald Radian",
    "listingType": "ListingWithoutPhotos",
    "customListingId": "0",
    "purchasePrice": 0.16,
    "shippingPrice": 0,
    "orderDate": "2025-05-18T00:10:55.3+00:00"
  },
  {
    "condition": "Near Mint",
    "variant": "Normal",
    "language": "English",
    "quantity": 1,
    "title": "Aatchik, Emerald Radian",
    "listingType": "ListingWithoutPhotos",
    "customListingId": "0",
    "purchasePrice": 0.15,
    "shippingPrice": 1.99,
    "orderDate": "2025-05-17T19:17:26.04+00:00"
  },
  {
    "condition": "Near Mint",
    "variant": "Normal",
    "language": "English",
    "quantity": 1,
    "title": "Aatchik, Emerald Radian",
    "listingType": "ListingWithoutPhotos",
    "customListingId": "0",
    "purchasePrice": 0.16,
    "shippingPrice": 0,
    "orderDate": "2025-05-17T04:04:52.47+00:00"
  },
  {
    "condition": "Near Mint",
    "variant": "Normal",
    "language": "English",
    "quantity": 1,
    "title": "Aatchik, Emerald Radian",
    "listingType": "ListingWithoutPhotos",
    "customListingId": "0",
    "purchasePrice": 0.16,
    "shippingPrice": 0,
    "orderDate": "2025-05-17T02:59:22.957+00:00"
  },
  {
    "condition": "Near Mint",
    "variant": "Normal",
    "language": "English",
    "quantity": 1,
    "title": "Aatchik, Emerald Radian",
    "listingType": "ListingWithoutPhotos",
    "customListingId": "0",
    "purchasePrice": 0.07,
    "shippingPrice": 1.31,
    "orderDate": "2025-05-17T02:29:07.497+00:00"
  },
  {
    "condition": "Near Mint",
    "variant": "Normal",
    "language": "English",
    "quantity": 1,
    "title": "Aatchik, Emerald Radian",
    "listingType": "ListingWithoutPhotos",
    "customListingId": "0",
    "purchasePrice": 0.16,
    "shippingPrice": 0,
    "orderDate": "2025-05-17T02:11:57.527+00:00"
  },
  {
    "condition": "Near Mint",
    "variant": "Normal",
    "language": "English",
    "quantity": 1,
    "title": "Aatchik, Emerald Radian",
    "listingType": "ListingWithoutPhotos",
    "customListingId": "0",
    "purchasePrice": 0.07,
    "shippingPrice": 1.31,
    "orderDate": "2025-05-17T01:19:40.877+00:00"
  },
  {
    "condition": "Near Mint",
    "variant": "Normal",
    "language": "English",
    "quantity": 1,
    "title": "Aatchik, Emerald Radian",
    "listingType": "ListingWithoutPhotos",
    "customListingId": "0",
    "purchasePrice": 0.15,
    "shippingPrice": 0,
    "orderDate": "2025-05-17T00:02:36.187+00:00"
  },
  {
    "condition": "Near Mint",
    "variant": "Normal",
    "language": "English",
    "quantity": 1,
    "title": "Aatchik, Emerald Radian",
    "listingType": "ListingWithoutPhotos",
    "customListingId": "0",
    "purchasePrice": 0.16,
    "shippingPrice": 0,
    "orderDate": "2025-05-16T20:28:57.88+00:00"
  },
  {
    "condition": "Near Mint",
    "variant": "Normal",
    "language": "English",
    "quantity": 1,
    "title": "Aatchik, Emerald Radian",
    "listingType": "ListingWithoutPhotos",
    "customListingId": "0",
    "purchasePrice": 0.16,
    "shippingPrice": 0,
    "orderDate": "2025-05-16T19:56:26.76+00:00"
  },
  {
    "condition": "Near Mint",
    "variant": "Normal",
    "language": "English",
    "quantity": 1,
    "title": "Aatchik, Emerald Radian",
    "listingType": "ListingWithoutPhotos",
    "customListingId": "0",
    "purchasePrice": 0.07,
    "shippingPrice": 1.31,
    "orderDate": "2025-05-16T19:37:16.98+00:00"
  },
  {
    "condition": "Near Mint",
    "variant": "Normal",
    "language": "English",
    "quantity": 1,
    "title": "Aatchik, Emerald Radian",
    "listingType": "ListingWithoutPhotos",
    "customListingId": "0",
    "purchasePrice": 0.17,
    "shippingPrice": 1.5,
    "orderDate": "2025-05-16T18:51:22.31+00:00"
  },
  {
    "condition": "Near Mint",
    "variant": "Normal",
    "language": "English",
    "quantity": 1,
    "title": "Aatchik, Emerald Radian",
    "listingType": "ListingWithoutPhotos",
    "customListingId": "0",
    "purchasePrice": 0.2,
    "shippingPrice": 0,
    "orderDate": "2025-05-16T18:31:35.237+00:00"
  }
]